secure_mail/__init__.py
secure_mail/admin.py
secure_mail/apps.py
secure_mail/backends.py
secure_mail/checks.py
secure_mail/forms.py
secure_mail/handlers.py
secure_mail/models.py
secure_mail/settings.py
secure_mail/utils.py
secure_mail/management/__init__.py
secure_mail/management/commands/__init__.py
secure_mail/management/commands/email_signing_key.py
secure_mail/migrations/0001_initial.py
secure_mail/migrations/__init__.py
secure_mail/templates/admin/secure_mail/address/change_form.html
secure_mail/templates/admin/secure_mail/key/change_form.html
tests/integration/__init__.py
tests/integration/test_admin.py
tests/integration/test_apps.py
tests/integration/test_backends.py
tests/integration/test_command.py
tests/integration/test_forms.py
tests/integration/test_handlers.py
tests/integration/test_models.py
tests/unit/__init__.py
tests/unit/test_utils.py
django_secure_mail-1.3.0.dist-info/AUTHORS
django_secure_mail-1.3.0.dist-info/LICENSE
django_secure_mail-1.3.0.dist-info/METADATA
django_secure_mail-1.3.0.dist-info/WHEEL
django_secure_mail-1.3.0.dist-info/top_level.txt
django_secure_mail-1.3.0.dist-info/RECORD
