Metadata-Version: 2.1
Name: django-secure-mail
Version: 1.3.0
Summary: A Django reusable app providing the ability to send PGP encrypted and multipart emails using the Django templating system.
Home-page: https://github.com/blag/django-secure-mail
Author: blag
Author-email: blag@users.noreply.github.com
License: UNKNOWN
Platform: UNKNOWN
Classifier: Development Status :: 5 - Production/Stable
Classifier: Environment :: Web Environment
Classifier: Intended Audience :: Developers
Classifier: Operating System :: OS Independent
Classifier: Programming Language :: Python
Classifier: Programming Language :: Python :: 3
Classifier: Programming Language :: Python :: 3.6
Classifier: Programming Language :: Python :: 3.7
Classifier: Programming Language :: Python :: 3.8
Classifier: Framework :: Django
Classifier: Topic :: Communications :: Email
Classifier: Topic :: Security :: Cryptography
Requires-Dist: django
Requires-Dist: python-gnupg
Provides-Extra: dev
Requires-Dist: check-manifest ; extra == 'dev'
Requires-Dist: sphinx-me ; extra == 'dev'
Requires-Dist: twine ; extra == 'dev'
Provides-Extra: test
Requires-Dist: coverage ; extra == 'test'
Requires-Dist: flake8 ; extra == 'test'
